popstarlight/__init__.py
popstarlight/ferre.py
popstarlight/ssp.py
popstarlight/utils.py
popstarlight-1.0.0.dist-info/LICENSE
popstarlight-1.0.0.dist-info/METADATA
popstarlight-1.0.0.dist-info/WHEEL
popstarlight-1.0.0.dist-info/top_level.txt
popstarlight-1.0.0.dist-info/RECORD
