Metadata-Version: 2.1
Name: popstarlight
Version: 1.0.0
Summary: SSP synthetic spectra
Home-page: https://github.com/dnidever/popstarlight
Author: David Nidever
Author-email: dnidever@montana.edu
License: MIT
Requires-Python: >=3.6
License-File: LICENSE
Requires-Dist: numpy
Requires-Dist: astropy (>=4.0)
Requires-Dist: scipy
Requires-Dist: dlnpyutils (>=1.0.3)
Requires-Dist: ferre
Requires-Dist: gdown
Provides-Extra: docs
Requires-Dist: sphinx ; extra == 'docs'
Requires-Dist: sphinx-astropy ; extra == 'docs'
Requires-Dist: nbsphinx ; extra == 'docs'
Requires-Dist: nbconvert ; extra == 'docs'
Requires-Dist: nbformat ; extra == 'docs'
Requires-Dist: ipykernel ; extra == 'docs'
Provides-Extra: test
Requires-Dist: pytest ; extra == 'test'
Requires-Dist: pytest-astropy ; extra == 'test'
Requires-Dist: ipython ; extra == 'test'
